foam_gen/__init__.py
foam_gen/__main__.py
foam_gen/__version__.py
foam_gen/src/__init__.py
foam_gen/src/analysis/AdjustDensities.py
foam_gen/src/analysis/Generate_Foam_Batches.py
foam_gen/src/analysis/ML_Density_Adjustment.py
foam_gen/src/analysis/ML_Density_AdjustmentFit.py
foam_gen/src/analysis/Sort_radii.py
foam_gen/src/analysis/batch_generators.py
foam_gen/src/analysis/get_real_distributions.py
foam_gen/src/analysis/lognormal_dists_plotly.py
foam_gen/src/analysis/plot_hist_of_real_dists.py
foam_gen/src/analysis/updated_radii.py
foam_gen/src/calcs/__init__.py
foam_gen/src/calcs/calcs.py
foam_gen/src/draw/__init__.py
foam_gen/src/draw/draw.py
foam_gen/src/make_foam/__init__.py
foam_gen/src/make_foam/atomic.py
foam_gen/src/make_foam/distributions.py
foam_gen/src/make_foam/standard.py
foam_gen/src/output/__init__.py
foam_gen/src/output/output.py
foam_gen/src/system/__init__.py
foam_gen/src/system/system.py
foam_gen/src/visualize/GUI.py
foam_gen/src/visualize/GUI2.py
foam_gen/src/visualize/__init__.py
foam_gen/src/visualize/mpl_visualize.py
foamify-0.1.0.dist-info/licenses/LICENSE
foamify-0.1.0.dist-info/METADATA
foamify-0.1.0.dist-info/WHEEL
foamify-0.1.0.dist-info/entry_points.txt
foamify-0.1.0.dist-info/top_level.txt
foamify-0.1.0.dist-info/RECORD
