Metadata-Version: 2.4
Name: foamify
Version: 0.1.0
Summary: An interactive simulated foam generator for creating 3-dimensional random ensembles of spheres
Home-page: https://github.com/jackericson98/foamify
Author: John Ericson
Author-email: John Ericson <jackericson98@gmail.com>
License-Expression: MIT
Project-URL: Homepage, https://github.com/jackericson98/foamify
Project-URL: Repository, https://github.com/jackericson98/foamify
Project-URL: Documentation, https://github.com/jackericson98/foamify#readme
Project-URL: Bug Tracker, https://github.com/jackericson98/foamify/issues
Keywords: foam,simulation,3d,spheres,physics,visualization
Classifier: Development Status :: 3 - Alpha
Classifier: Intended Audience :: Science/Research
Classifier: Topic :: Scientific/Engineering :: Physics
Classifier: Topic :: Scientific/Engineering :: Visualization
Classifier: Programming Language :: Python :: 3
Classifier: Programming Language :: Python :: 3.8
Classifier: Programming Language :: Python :: 3.9
Classifier: Programming Language :: Python :: 3.10
Classifier: Programming Language :: Python :: 3.11
Classifier: Programming Language :: Python :: 3.12
Classifier: Operating System :: OS Independent
Requires-Python: >=3.8
License-File: LICENSE
Requires-Dist: numpy>=1.21.0
Requires-Dist: scipy>=1.7.0
Requires-Dist: matplotlib>=3.5.0
Requires-Dist: numba>=0.56.0
Requires-Dist: pandas>=1.3.0
Requires-Dist: scikit-learn>=1.0.0
Requires-Dist: tqdm>=4.62.0
Dynamic: author
Dynamic: home-page
Dynamic: license-file
Dynamic: requires-python
